LICENSE
setup.cfg
setup.py
pacote_coupa/converter_xlsx_para_csv.py
pacote_coupa/gerar_csv.py
pacote_coupa/get_api.py
pacote_coupa/pegar_salvar_arquivo.py
pacote_coupa.egg-info/PKG-INFO
pacote_coupa.egg-info/SOURCES.txt
pacote_coupa.egg-info/dependency_links.txt
pacote_coupa.egg-info/requires.txt
pacote_coupa.egg-info/top_level.txt