Metadata-Version: 2.1
Name: pacote-coupa
Version: 0.0.1
Summary: Meu exemplo de pacote PyPI
Home-page: UNKNOWN
Author: Danilo Oliveira
Author-email: danilo.o.r.santos@gmail.com
License: MIT License
Keywords: Pacote
Platform: UNKNOWN
License-File: LICENSE
